add_ascertainment/__init__.py
add_ascertainment/__main__.py
add_ascertainment-0.0.1.dist-info/LICENSE
add_ascertainment-0.0.1.dist-info/METADATA
add_ascertainment-0.0.1.dist-info/WHEEL
add_ascertainment-0.0.1.dist-info/entry_points.txt
add_ascertainment-0.0.1.dist-info/RECORD
