Metadata-Version: 2.1
Name: add_ascertainment
Version: 0.0.1
Summary: Add Ascertainment Characters to Nexus File
Home-page: https://github.com/SimonGreenhill/add_ascertainment
License: MIT
Author: Simon Greenhill
Author-email: simon@simon.net.nz
Requires-Python: >=3.7,<4.0
Classifier: License :: OSI Approved :: MIT License
Classifier: Programming Language :: Python :: 3
Classifier: Programming Language :: Python :: 3.7
Classifier: Programming Language :: Python :: 3.8
Classifier: Programming Language :: Python :: 3.9
Classifier: Programming Language :: Python :: 3.10
Classifier: Programming Language :: Python :: 3.11
Classifier: Programming Language :: Python :: 3.12
Requires-Dist: python-nexus (>=2.9.0,<3.0.0)
Project-URL: Documentation, https://github.com/SimonGreenhill/add_ascertainment
Project-URL: Repository, https://github.com/SimonGreenhill/add_ascertainment
